README.md
setup.py
holographic/__init__.py
holographic/file_watcher.py
holographic/import_hooks.py
holographic/models.py
holographic/server.py
holographic/tests.py
holographic.egg-info/PKG-INFO
holographic.egg-info/SOURCES.txt
holographic.egg-info/dependency_links.txt
holographic.egg-info/requires.txt
holographic.egg-info/top_level.txt