Metadata-Version: 2.1
Name: holographic
Version: 0.0.1
Summary: This is ground control to Major Tom...
Home-page: UNKNOWN
Author: Max Taggart
Author-email: max.taggart@healthcatalyst.com
License: UNKNOWN
Platform: UNKNOWN
Classifier: Programming Language :: Python :: 3.10
Classifier: License :: OSI Approved :: MIT License
Classifier: Operating System :: OS Independent
